setup.py
django_stage/__init__.py
django_stage.egg-info/PKG-INFO
django_stage.egg-info/SOURCES.txt
django_stage.egg-info/dependency_links.txt
django_stage.egg-info/top_level.txt
django_stage.egg-info/zip-safe