Metadata-Version: 1.1
Name: django-stage
Version: 0.0.1
Summary: Manage django stage settings.
Home-page: https://github.com/kelonye/django-stage
Author: Mitchel Kelonye
Author-email: kelonyemitchel@gmail.com
License: MIT License
Platform: UNKNOWN
Requires: Django (>=1.3.0)
